{"cameraMode":{"drawMode":0,"name":"Shaded","section":"Shading Mode"},"sceneLighting":true,"audioPlay":false,"sceneViewState":{"m_AlwaysRefresh":false,"showFog":true,"showSkybox":true,"showFlares":true,"showImageEffects":true,"showParticleSystems":true,"showVisualEffectGraphs":true,"m_FxEnabled":true},"in2DMode":false,"pivot":{"x":252.0,"y":761.5,"z":0.0},"rotation":{"x":-0.031804196536540988,"y":-0.0009026277693919838,"z":0.00002865160786313936,"w":-0.999493420124054},"size":701.877685546875,"orthographic":false}